spheres_packing_calculator/__init__.py
spheres_packing_calculator/spheres_packing_calculator.py
spheres_packing_calculator-0.1.4.dist-info/LICENCE
spheres_packing_calculator-0.1.4.dist-info/METADATA
spheres_packing_calculator-0.1.4.dist-info/WHEEL
spheres_packing_calculator-0.1.4.dist-info/top_level.txt
spheres_packing_calculator-0.1.4.dist-info/RECORD
