Metadata-Version: 2.1
Name: spheres_packing_calculator
Version: 0.1.4
Summary: Calculates a precise packing density for spherical particles in a 3d cartesian region
Author-email: Freddie Barter <fjbarter@outlook.com>
License: GPL
Requires-Python: >=3.6
License-File: LICENCE
Requires-Dist: numpy
Requires-Dist: scipy
Requires-Dist: pyvista
